{
	"info": {
		"_postman_id": "aeae6493-bf2f-4100-bc96-a2ca113d56b7",
		"name": "AI Tutor",
		"schema": "https://schema.getpostman.com/json/collection/v2.1.0/collection.json",
		"_exporter_id": "184128"
	},
	"item": [
		{
			"name": "Create Experiment",
			"request": {
				"method": "POST",
				"header": [],
				"body": {
					"mode": "raw",
					"raw": "{\n    \"problem\": \"Display Fibonacci series up to a given number\"\n}",
					"options": {
						"raw": {
							"language": "json"
						}
					}
				},
				"url": {
					"raw": "http://localhost:8080/api/experiments",
					"protocol": "http",
					"host": [
						"localhost"
					],
					"port": "8080",
					"path": [
						"api",
						"experiments"
					]
				}
			},
			"response": [
				{
					"name": "Fibonacci Experiment",
					"originalRequest": {
						"method": "POST",
						"header": [],
						"body": {
							"mode": "raw",
							"raw": "{\n    \"problem\": \"Display Fibonacci series up to a given number\"\n}",
							"options": {
								"raw": {
									"language": "json"
								}
							}
						},
						"url": {
							"raw": "http://localhost:8080/api/experiments",
							"protocol": "http",
							"host": [
								"localhost"
							],
							"port": "8080",
							"path": [
								"api",
								"experiments"
							]
						}
					},
					"status": "Created",
					"code": 201,
					"_postman_previewlanguage": "json",
					"header": [
						{
							"key": "Content-Type",
							"value": "application/json"
						},
						{
							"key": "Transfer-Encoding",
							"value": "chunked"
						},
						{
							"key": "Date",
							"value": "Tue, 01 Aug 2023 14:57:25 GMT"
						},
						{
							"key": "Keep-Alive",
							"value": "timeout=60"
						},
						{
							"key": "Connection",
							"value": "keep-alive"
						}
					],
					"cookie": [],
					"body": "{\n    \"id\": 1,\n    \"problem\": \"Display Fibonacci series up to a given number\"\n}"
				}
			]
		},
		{
			"name": "Get All Experiments",
			"request": {
				"method": "GET",
				"header": [],
				"url": {
					"raw": "http://localhost:8080/api/experiments",
					"protocol": "http",
					"host": [
						"localhost"
					],
					"port": "8080",
					"path": [
						"api",
						"experiments"
					]
				}
			},
			"response": [
				{
					"name": "Get All Experiments Sample",
					"originalRequest": {
						"method": "GET",
						"header": [],
						"url": {
							"raw": "http://localhost:8080/api/experiments",
							"protocol": "http",
							"host": [
								"localhost"
							],
							"port": "8080",
							"path": [
								"api",
								"experiments"
							]
						}
					},
					"status": "OK",
					"code": 200,
					"_postman_previewlanguage": "json",
					"header": [
						{
							"key": "Content-Type",
							"value": "application/json"
						},
						{
							"key": "Transfer-Encoding",
							"value": "chunked"
						},
						{
							"key": "Date",
							"value": "Tue, 01 Aug 2023 14:57:41 GMT"
						},
						{
							"key": "Keep-Alive",
							"value": "timeout=60"
						},
						{
							"key": "Connection",
							"value": "keep-alive"
						}
					],
					"cookie": [],
					"body": "[\n    {\n        \"id\": 1,\n        \"problem\": \"Display Fibonacci series up to a given number\"\n    }\n]"
				}
			]
		},
		{
			"name": "Get Experiment",
			"request": {
				"method": "GET",
				"header": [],
				"url": {
					"raw": "http://localhost:8080/api/experiments/1",
					"protocol": "http",
					"host": [
						"localhost"
					],
					"port": "8080",
					"path": [
						"api",
						"experiments",
						"1"
					]
				}
			},
			"response": [
				{
					"name": "Get Fibonacci Experiment",
					"originalRequest": {
						"method": "GET",
						"header": [],
						"url": {
							"raw": "http://localhost:8080/api/experiments/1",
							"protocol": "http",
							"host": [
								"localhost"
							],
							"port": "8080",
							"path": [
								"api",
								"experiments",
								"1"
							]
						}
					},
					"status": "OK",
					"code": 200,
					"_postman_previewlanguage": "json",
					"header": [
						{
							"key": "Content-Type",
							"value": "application/json"
						},
						{
							"key": "Transfer-Encoding",
							"value": "chunked"
						},
						{
							"key": "Date",
							"value": "Tue, 01 Aug 2023 14:56:36 GMT"
						},
						{
							"key": "Keep-Alive",
							"value": "timeout=60"
						},
						{
							"key": "Connection",
							"value": "keep-alive"
						}
					],
					"cookie": [],
					"body": "{\n    \"id\": 1,\n    \"problem\": \"Display Fibonacci series up to a given number\"\n}"
				}
			]
		},
		{
			"name": "Get Experiment Metrics",
			"request": {
				"method": "GET",
				"header": [],
				"url": {
					"raw": "http://localhost:8080/api/experiments/1/metrics",
					"protocol": "http",
					"host": [
						"localhost"
					],
					"port": "8080",
					"path": [
						"api",
						"experiments",
						"1",
						"metrics"
					]
				}
			},
			"response": [
				{
					"name": "Metrics For Fibonacci Experiment",
					"originalRequest": {
						"method": "GET",
						"header": [],
						"url": {
							"raw": "http://localhost:8080/api/experiments/1/metrics",
							"protocol": "http",
							"host": [
								"localhost"
							],
							"port": "8080",
							"path": [
								"api",
								"experiments",
								"1",
								"metrics"
							]
						}
					},
					"status": "OK",
					"code": 200,
					"_postman_previewlanguage": "json",
					"header": [
						{
							"key": "Content-Type",
							"value": "application/json"
						},
						{
							"key": "Transfer-Encoding",
							"value": "chunked"
						},
						{
							"key": "Date",
							"value": "Tue, 01 Aug 2023 14:59:58 GMT"
						},
						{
							"key": "Keep-Alive",
							"value": "timeout=60"
						},
						{
							"key": "Connection",
							"value": "keep-alive"
						}
					],
					"cookie": [],
					"body": "[\n    {\n        \"id\": 1,\n        \"experimentId\": 1,\n        \"details\": null,\n        \"timestamp\": \"2023-08-01T14:57:25.935351Z\",\n        \"metricType\": \"CREATED\"\n    },\n    {\n        \"id\": 2,\n        \"experimentId\": 1,\n        \"details\": \"INCORRECT\",\n        \"timestamp\": \"2023-08-01T14:58:45.492509Z\",\n        \"metricType\": \"EXECUTION\"\n    },\n    {\n        \"id\": 3,\n        \"experimentId\": 1,\n        \"details\": \"CORRECT\",\n        \"timestamp\": \"2023-08-01T14:59:07.821548Z\",\n        \"metricType\": \"EXECUTION\"\n    },\n    {\n        \"id\": 4,\n        \"experimentId\": 1,\n        \"details\": \"Hint - \\n\\nTry adding a line of code to update\",\n        \"timestamp\": \"2023-08-01T14:59:36.065855Z\",\n        \"metricType\": \"HINT\"\n    }\n]"
				}
			]
		},
		{
			"name": "Execute Experiment With Incorrect Code",
			"request": {
				"method": "POST",
				"header": [],
				"body": {
					"mode": "raw",
					"raw": "{\n    \"code\": \"class Fibonacci {\\n  public static void main(String[] args) {\\n\\n    int n = 100, firstTerm = 0, secondTerm = 1;\\n        \\n    System.out.println(\\\"Fibonacci Series Upto \\\" + n + \\\": \\\");\\n    \\n    while (firstTerm <= n) {\\n      System.out.print(firstTerm + \\\", \\\");\\n\\n      firstTerm = secondTerm;\\n      secondTerm = nextTerm;\\n\\n    }\\n  }\\n}\"   \n}",
					"options": {
						"raw": {
							"language": "json"
						}
					}
				},
				"url": {
					"raw": "http://localhost:8080/api/experiments/1/execute",
					"protocol": "http",
					"host": [
						"localhost"
					],
					"port": "8080",
					"path": [
						"api",
						"experiments",
						"1",
						"execute"
					]
				}
			},
			"response": [
				{
					"name": "Incomplete Fibonacci Code",
					"originalRequest": {
						"method": "POST",
						"header": [],
						"body": {
							"mode": "raw",
							"raw": "{\n    \"code\": \"class Fibonacci {\\n  public static void main(String[] args) {\\n\\n    int n = 100, firstTerm = 0, secondTerm = 1;\\n        \\n    System.out.println(\\\"Fibonacci Series Upto \\\" + n + \\\": \\\");\\n    \\n    while (firstTerm <= n) {\\n      System.out.print(firstTerm + \\\", \\\");\\n\\n      firstTerm = secondTerm;\\n      secondTerm = nextTerm;\\n\\n    }\\n  }\\n}\"   \n}",
							"options": {
								"raw": {
									"language": "json"
								}
							}
						},
						"url": {
							"raw": "http://localhost:8080/api/experiments/1/execute",
							"protocol": "http",
							"host": [
								"localhost"
							],
							"port": "8080",
							"path": [
								"api",
								"experiments",
								"1",
								"execute"
							]
						}
					},
					"status": "OK",
					"code": 200,
					"_postman_previewlanguage": "json",
					"header": [
						{
							"key": "Content-Type",
							"value": "application/json"
						},
						{
							"key": "Content-Length",
							"value": "24"
						},
						{
							"key": "Date",
							"value": "Tue, 01 Aug 2023 14:58:45 GMT"
						},
						{
							"key": "Keep-Alive",
							"value": "timeout=60"
						},
						{
							"key": "Connection",
							"value": "keep-alive"
						}
					],
					"cookie": [],
					"body": "Your code is not correct"
				}
			]
		},
		{
			"name": "Execute Experiment With Correct Code",
			"request": {
				"method": "POST",
				"header": [],
				"body": {
					"mode": "raw",
					"raw": "{\n    \"code\": \"class Fibonacci {\\n  public static void main(String[] args) {\\n\\n    int n = 100, firstTerm = 0, secondTerm = 1;\\n        \\n    System.out.println(\\\"Fibonacci Series Upto \\\" + n + \\\": \\\");\\n    \\n    while (firstTerm <= n) {\\n      System.out.print(firstTerm + \\\", \\\");\\n\\n      int nextTerm = firstTerm + secondTerm;\\n      firstTerm = secondTerm;\\n      secondTerm = nextTerm;\\n\\n    }\\n  }\\n}\"   \n}",
					"options": {
						"raw": {
							"language": "json"
						}
					}
				},
				"url": {
					"raw": "http://localhost:8080/api/experiments/1/execute",
					"protocol": "http",
					"host": [
						"localhost"
					],
					"port": "8080",
					"path": [
						"api",
						"experiments",
						"1",
						"execute"
					]
				}
			},
			"response": [
				{
					"name": "Correct Fibonacci Code",
					"originalRequest": {
						"method": "POST",
						"header": [],
						"body": {
							"mode": "raw",
							"raw": "{\n    \"code\": \"class Fibonacci {\\n  public static void main(String[] args) {\\n\\n    int n = 100, firstTerm = 0, secondTerm = 1;\\n        \\n    System.out.println(\\\"Fibonacci Series Upto \\\" + n + \\\": \\\");\\n    \\n    while (firstTerm <= n) {\\n      System.out.print(firstTerm + \\\", \\\");\\n\\n      int nextTerm = firstTerm + secondTerm;\\n      firstTerm = secondTerm;\\n      secondTerm = nextTerm;\\n\\n    }\\n  }\\n}\"   \n}",
							"options": {
								"raw": {
									"language": "json"
								}
							}
						},
						"url": {
							"raw": "http://localhost:8080/api/experiments/1/execute",
							"protocol": "http",
							"host": [
								"localhost"
							],
							"port": "8080",
							"path": [
								"api",
								"experiments",
								"1",
								"execute"
							]
						}
					},
					"status": "OK",
					"code": 200,
					"_postman_previewlanguage": "json",
					"header": [
						{
							"key": "Content-Type",
							"value": "application/json"
						},
						{
							"key": "Content-Length",
							"value": "20"
						},
						{
							"key": "Date",
							"value": "Tue, 01 Aug 2023 14:59:07 GMT"
						},
						{
							"key": "Keep-Alive",
							"value": "timeout=60"
						},
						{
							"key": "Connection",
							"value": "keep-alive"
						}
					],
					"cookie": [],
					"body": "Your code is correct"
				}
			]
		},
		{
			"name": "Generate Hint For Incorrect Code",
			"request": {
				"method": "POST",
				"header": [],
				"body": {
					"mode": "raw",
					"raw": "{\n    \"prompt\": \"Assume that you are a programming teacher, and your intent is to help a student solve the given problem. You know the solution of the problem already. Your job is to analyse the student’s submitted code, and give him a hint that helps him solve the problem. Remember, you have to give the hint, not give him complete solution. \\n\\n\\n\\nProblem - \\n\\n${problem}” \\n\\n\\n\\nStudent’s input - \\n\\n${student_code}”\",\n    \"code\": \"class Fibonacci {\\n  public static void main(String[] args) {\\n\\n    int n = 100, firstTerm = 0, secondTerm = 1;\\n        \\n    System.out.println(\\\"Fibonacci Series Upto \\\" + n + \\\": \\\");\\n    \\n    while (firstTerm <= n) {\\n      System.out.print(firstTerm + \\\", \\\");\\n\\n      int nextTerm = firstTerm + secondTerm;\\n      secondTerm = nextTerm;\\n\\n    }\\n  }\\n}\"\n}",
					"options": {
						"raw": {
							"language": "json"
						}
					}
				},
				"url": {
					"raw": "http://localhost:8080/api/experiments/1/hints",
					"protocol": "http",
					"host": [
						"localhost"
					],
					"port": "8080",
					"path": [
						"api",
						"experiments",
						"1",
						"hints"
					]
				}
			},
			"response": [
				{
					"name": "Generate Hint For Incorrect Fibonacci Code",
					"originalRequest": {
						"method": "POST",
						"header": [],
						"body": {
							"mode": "raw",
							"raw": "{\n    \"prompt\": \"Assume that you are a programming teacher, and your intent is to help a student solve the given problem. You know the solution of the problem already. Your job is to analyse the student’s submitted code, and give him a hint that helps him solve the problem. Remember, you have to give the hint, not give him complete solution. \\n\\n\\n\\nProblem - \\n\\n${problem}” \\n\\n\\n\\nStudent’s input - \\n\\n${student_code}”\",\n    \"code\": \"class Fibonacci {\\n  public static void main(String[] args) {\\n\\n    int n = 100, firstTerm = 0, secondTerm = 1;\\n        \\n    System.out.println(\\\"Fibonacci Series Upto \\\" + n + \\\": \\\");\\n    \\n    while (firstTerm <= n) {\\n      System.out.print(firstTerm + \\\", \\\");\\n\\n      int nextTerm = firstTerm + secondTerm;\\n      secondTerm = nextTerm;\\n\\n    }\\n  }\\n}\"\n}",
							"options": {
								"raw": {
									"language": "json"
								}
							}
						},
						"url": {
							"raw": "http://localhost:8080/api/experiments/1/hints",
							"protocol": "http",
							"host": [
								"localhost"
							],
							"port": "8080",
							"path": [
								"api",
								"experiments",
								"1",
								"hints"
							]
						}
					},
					"status": "OK",
					"code": 200,
					"_postman_previewlanguage": "json",
					"header": [
						{
							"key": "Content-Type",
							"value": "application/json"
						},
						{
							"key": "Content-Length",
							"value": "44"
						},
						{
							"key": "Date",
							"value": "Tue, 01 Aug 2023 14:59:36 GMT"
						},
						{
							"key": "Keep-Alive",
							"value": "timeout=60"
						},
						{
							"key": "Connection",
							"value": "keep-alive"
						}
					],
					"cookie": [],
					"body": "Hint - \n\nTry adding a line of code to update"
				}
			]
		}
	]
}